[
	{
		"__TYPE__": "SharedSliceContent",
		"variation": "default",
		"primary": {
			"heading": {
				"__TYPE__": "StructuredTextContent",
				"value": [
					{
						"type": "heading2",
						"content": {
							"text": "Flight"
						}
					}
				]
			},
			"description": {
				"__TYPE__": "StructuredTextContent",
				"value": [
					{
						"type": "paragraph",
						"content": {
							"text": "Minim est ipsum nulla occaecat laborum commodo pariatur magna eu. Ea quis exercitation non consequat amet sit ut laborum."
						}
					}
				]
			},
			"swithces": {
				"__TYPE__": "GroupContentType",
				"value": [
					{
						"__TYPE__": "GroupItemContent",
						"value": [
							[
								"switch",
								{
									"__TYPE__": "LinkContent",
									"key": "1751f9b7-51d3-48e8-a5cc-f578513f31f9",
									"value": {
										"__TYPE__": "DocumentLink",
										"id": "mock_document_id"
									}
								}
							]
						]
					}
				]
			}
		},
		"items": []
	}
]